djangorealtime/__init__.py
djangorealtime/admin.py
djangorealtime/apps.py
djangorealtime/config.py
djangorealtime/hooks.py
djangorealtime/listener.py
djangorealtime/models.py
djangorealtime/publisher.py
djangorealtime/queues.py
djangorealtime/retry.py
djangorealtime/signals.py
djangorealtime/structs.py
djangorealtime/thread_pool.py
djangorealtime/urls.py
djangorealtime/utils.py
djangorealtime/views.py
djangorealtime/backends/__init__.py
djangorealtime/backends/base.py
djangorealtime/backends/postgresql.py
djangorealtime/backends/utils.py
djangorealtime/migrations/0001_initial.py
djangorealtime/migrations/__init__.py
djangorealtime/static/djangorealtime/js/realtime.js
djangorealtime/templatetags/__init__.py
djangorealtime/templatetags/djangorealtime_tags.py
djrealtime-1.0.4.dist-info/licenses/LICENSE
djrealtime-1.0.4.dist-info/METADATA
djrealtime-1.0.4.dist-info/WHEEL
djrealtime-1.0.4.dist-info/top_level.txt
djrealtime-1.0.4.dist-info/RECORD
