Metadata-Version: 2.4
Name: djrealtime
Version: 1.0.4
Summary: Realtime browser events for Django + PostgreSQL
Author-email: Muhammad Usman <hi@usman.it>
Classifier: Framework :: Django
Classifier: Programming Language :: Python :: 3
Classifier: License :: OSI Approved :: MIT License
Requires-Python: >=3.10
License-File: LICENSE
Requires-Dist: Django>=5.0
Requires-Dist: psycopg[binary]
Provides-Extra: dev
Requires-Dist: pytest; extra == "dev"
Requires-Dist: pytest-django; extra == "dev"
Requires-Dist: pytest-cov; extra == "dev"
Requires-Dist: pytest-asyncio; extra == "dev"
Requires-Dist: ruff; extra == "dev"
Dynamic: license-file
